neuralcoref/neuralcoref.cpython-37m-x86_64-linux-gnu.so
neuralcoref/file_utils.py
neuralcoref/__init__.py
neuralcoref/train/learn.py
neuralcoref/train/algorithm.py
neuralcoref/train/utils.py
neuralcoref/train/conllparser.py
neuralcoref/train/evaluator.py
neuralcoref/train/compat.py
neuralcoref/train/dataset.py
neuralcoref/train/document.py
neuralcoref/train/__init__.py
neuralcoref/train/model.py
neuralcoref/tests/test_neuralcoref.py
neuralcoref/tests/__init__.py
neuralcoref-4.0.dist-info/top_level.txt
neuralcoref-4.0.dist-info/RECORD
neuralcoref-4.0.dist-info/METADATA
neuralcoref-4.0.dist-info/WHEEL
